Metadata-Version: 1.1
Name: spytec02
Version: 0.0.2
Summary: Includes math operations for more visit "https://dracoweb.herokuapp.com"
Home-page: UNKNOWN
Author: dragonspace
Author-email: UNKNOWN
License: UNKNOWN
Download-URL: https://dracoweb.herokuapp.com
Platform: UNKNOWN
Classifier: Programming Language :: Python :: 3
Classifier: License :: OSI Approved :: MIT License
Classifier: Operating System :: OS Independent
